atomic_red_team/__init__.py
atomic_red_team/__main__.py
atomic_red_team/art.py
atomic_red_team/atomic.py
atomic_red_team/helpers.py
atomic_red_team/atomic/__init__.py
atomic_red_team/atomic/loader.py
atomic_red_team/atomic/parser.py
atomic_red_team/atomic/testparser.py
atomic_red_team/utils/__init__.py
atomic_red_team/utils/exceptions.py
atomic_red_team/utils/logger.py
atomic_red_team/utils/version.py
atomic_red_team-0.0.1.dist-info/LICENSE.md
atomic_red_team-0.0.1.dist-info/METADATA
atomic_red_team-0.0.1.dist-info/WHEEL
atomic_red_team-0.0.1.dist-info/entry_points.txt
atomic_red_team-0.0.1.dist-info/top_level.txt
atomic_red_team-0.0.1.dist-info/RECORD
