Metadata-Version: 2.1
Name: atomic-red-team
Version: 0.0.1
Summary: A python package to execute Atomic tests
Home-page: https://github.com/MSAdministrator/atomic_red_team
Author: MSAdministrator
Author-email: rickardja@live.com
License: MIT
Keywords: atomic-red-team,att&ck,test,redcanary,mitre,executor
Platform: UNKNOWN
Requires-Python: >=3.6, <4
Requires-Dist: pyyaml (==5.4.1)
Requires-Dist: fire (==0.3.1)
Requires-Dist: unidecode (==1.2.0)
